odoo8_addon_l10n_nl_account_invoice_ubl-8.0.1.0.0.99.dev2-py3.8-nspkg.pth
odoo_addons/l10n_nl_account_invoice_ubl/README.rst
odoo_addons/l10n_nl_account_invoice_ubl/__init__.py
odoo_addons/l10n_nl_account_invoice_ubl/__openerp__.py
odoo_addons/l10n_nl_account_invoice_ubl/models/__init__.py
odoo_addons/l10n_nl_account_invoice_ubl/models/account_invoice_ubl.py
odoo_addons/l10n_nl_account_invoice_ubl/readme/CONTRIBUTORS.rst
odoo_addons/l10n_nl_account_invoice_ubl/readme/DESCRIPTION.rst
odoo_addons/l10n_nl_account_invoice_ubl/static/description/icon.png
odoo_addons/l10n_nl_account_invoice_ubl/static/description/index.html
odoo_addons/l10n_nl_account_invoice_ubl/tests/__init__.py
odoo_addons/l10n_nl_account_invoice_ubl/tests/test_ubl_invoice_nl.py
odoo8_addon_l10n_nl_account_invoice_ubl-8.0.1.0.0.99.dev2.dist-info/METADATA
odoo8_addon_l10n_nl_account_invoice_ubl-8.0.1.0.0.99.dev2.dist-info/WHEEL
odoo8_addon_l10n_nl_account_invoice_ubl-8.0.1.0.0.99.dev2.dist-info/namespace_packages.txt
odoo8_addon_l10n_nl_account_invoice_ubl-8.0.1.0.0.99.dev2.dist-info/top_level.txt
odoo8_addon_l10n_nl_account_invoice_ubl-8.0.1.0.0.99.dev2.dist-info/RECORD
