Metadata-Version: 2.1
Name: odoo8-addon-l10n-nl-account-invoice-ubl
Version: 8.0.1.0.0.99.dev2
Summary: Generate UBL invoices in Netherlands-specific UBL dialect (NLCIUS)
Home-page: https://github.com/OCA/l10n-netherlands
Author: Sunflower IT, Odoo Community Association (OCA)
Author-email: support@odoo-community.org
License: AGPL-3
Platform: UNKNOWN
Classifier: Programming Language :: Python
Classifier: Framework :: Odoo
Classifier: Framework :: Odoo :: 8.0
Classifier: License :: OSI Approved :: GNU Affero General Public License v3
Requires-Python: ~=2.7
Requires-Dist: odoo8-addon-account-invoice-ubl
Requires-Dist: odoo8-addon-l10n-nl-base-ubl
Requires-Dist: odoo (<9.0a,>=8.0a)
